Metadata-Version: 2.1
Name: vz-pytorch
Version: 0.1.3
Summary: Create Vizstack visualizations of Pytorch models.
Home-page: https://github.com/vizstack/vz-pytorch
Author: Ryan Holmdahl & Nikhil Bhattasali
Author-email: vizstack@gmail.com
License: MIT
Platform: UNKNOWN
